hermitage/__init__.py
hermitage/adapters/__init__.py
hermitage/adapters/constraints.py
hermitage/adapters/cqea.py
hermitage/adapters/transformers.py
hermitage/definitions/__init__.py
hermitage/definitions/contracts/__init__.py
hermitage/definitions/contracts/adapters.py
hermitage/notation/__init__.py
hermitage/notation/default.py
hermitage-0.3.4.dist-info/METADATA
hermitage-0.3.4.dist-info/WHEEL
hermitage-0.3.4.dist-info/RECORD
