Metadata-Version: 2.1
Name: hermitage
Version: 0.3.4
Summary: Universal storage access framework
Home-page: https://github.com/smairon/hermitage
Author: Smairon
Author-email: man@smairon.ru
Requires-Python: >=3.11,<4.0
Classifier: Programming Language :: Python :: 3
Classifier: Programming Language :: Python :: 3.11
Classifier: Programming Language :: Python :: 3.12
Requires-Dist: zodchy (>=0.4.2,<0.5.0)
Project-URL: Repository, https://github.com/smairon/hermitage
